{
	"configurations" : 
	[
		{
			"directories" : 
			[
				{
					"build" : ".",
					"hasInstallRule" : true,
					"jsonFile" : "directory-.-097e2b9ca714da460029.json",
					"minimumCMakeVersion" : 
					{
						"string" : "3.12"
					},
					"projectIndex" : 0,
					"source" : ".",
					"targetIndexes" : 
					[
						0,
						1
					]
				}
			],
			"name" : "",
			"projects" : 
			[
				{
					"directoryIndexes" : 
					[
						0
					],
					"name" : "geometry2",
					"targetIndexes" : 
					[
						0,
						1
					]
				}
			],
			"targets" : 
			[
				{
					"directoryIndex" : 0,
					"id" : "geometry2_uninstall::@6890427a1f51a3e7e1df",
					"jsonFile" : "target-geometry2_uninstall-97fea048cc9d792c553c.json",
					"name" : "geometry2_uninstall",
					"projectIndex" : 0
				},
				{
					"directoryIndex" : 0,
					"id" : "uninstall::@6890427a1f51a3e7e1df",
					"jsonFile" : "target-uninstall-624870c56692656676c6.json",
					"name" : "uninstall",
					"projectIndex" : 0
				}
			]
		}
	],
	"kind" : "codemodel",
	"paths" : 
	{
		"build" : "/home/yug/agv-alpharacer/alpha-RACER/ros2_ws/build/geometry2",
		"source" : "/home/yug/agv-alpharacer/alpha-RACER/ros2_ws/src/geometry2/geometry2"
	},
	"version" : 
	{
		"major" : 2,
		"minor" : 3
	}
}
